{
  "display": {
    "icon": {
      "item": "enderio:vibrant_capacitor_bank"
    },
    "title": "Vibrant Capacitor Bank",
    "description": "Store RF, like a battery!\n\nIt is a shapeless multiblock; putting a Vibrant Capacitor Bank next to another Vibrant Capacitor Bank will combine their energy storage. ",
    "frame": "task",
    "show_toast": true,
    "announce_to_chat": true,
    "hidden": false
  },
  "parent": "aprandomizer:archipelago/quest_advanced_capacitor_bank",
  "criteria": {
    "impossible": {
      "trigger": "minecraft:impossible"
    }
  }
}